.gitignore
CHANGELOG.rst
MANIFEST.in
README.rst
setup.cfg
setup.py
furnish/__init__.py
furnish/exc.py
furnish/types.py
furnish/utils.py
furnish.egg-info/PKG-INFO
furnish.egg-info/SOURCES.txt
furnish.egg-info/dependency_links.txt
furnish.egg-info/requires.txt
furnish.egg-info/top_level.txt
tests/fakeservice.py
tests/test_call.py
tests/test_class.py
tests/test_decorators.py