Metadata-Version: 1.1
Name: furnish
Version: 0.2.1
Summary: Create HTTP API clients from Python.
Home-page: https://github.com/everilae/furnish
Author: Ilja Everilä
Author-email: saarni@gmail.com
License: MIT
Download-URL: https://github.com/everilae/furnish/archive/v0.2.1.tar.gz
Platform: UNKNOWN
Classifier: Development Status :: 3 - Alpha
Classifier: License :: OSI Approved :: MIT License
Classifier: Programming Language :: Python :: 3
